pyln/client/__init__.py
pyln/client/clnutils.py
pyln/client/gossmap.py
pyln/client/gossmapstats.py
pyln/client/lightning.py
pyln/client/plugin.py
pyln/client/version.py
pyln_client-25.12.dist-info/METADATA
pyln_client-25.12.dist-info/WHEEL
pyln_client-25.12.dist-info/RECORD
