Metadata-Version: 2.4
Name: pyln-client
Version: 25.12
Summary: Client library and plugin library for Core Lightning
Author-email: Christian Decker <decker.christian@gmail.com>
License: BSD-MIT
Requires-Python: <4.0,>=3.9
Requires-Dist: pyln-bolt7>=1.0
Requires-Dist: pyln-proto>=23
